computer_use_ootb_internal/README.md
computer_use_ootb_internal/__init__.py
computer_use_ootb_internal/app_teachmode.py
computer_use_ootb_internal/dependency_check.py
computer_use_ootb_internal/guard_service.py
computer_use_ootb_internal/requirements-lite.txt
computer_use_ootb_internal/run_teachmode_ootb_args.py
computer_use_ootb_internal/service_manager.py
computer_use_ootb_internal/signal_connection.py
computer_use_ootb_internal/test_autogui.py
computer_use_ootb_internal/computer_use_demo/animation/click_animation.py
computer_use_ootb_internal/computer_use_demo/animation/icons8-select-cursor-transparent-96.gif
computer_use_ootb_internal/computer_use_demo/animation/test_animation.py
computer_use_ootb_internal/computer_use_demo/executor/teachmode_executor.py
computer_use_ootb_internal/computer_use_demo/gui_agent/gui_parser/simple_parser/__init__.py
computer_use_ootb_internal/computer_use_demo/gui_agent/gui_parser/simple_parser/gui_capture.py
computer_use_ootb_internal/computer_use_demo/gui_agent/gui_parser/simple_parser/utils.py
computer_use_ootb_internal/computer_use_demo/gui_agent/gui_parser/uia_tools/__init__.py
computer_use_ootb_internal/computer_use_demo/gui_agent/gui_parser/uia_tools/screenshot_cli.py
computer_use_ootb_internal/computer_use_demo/gui_agent/gui_parser/uia_tools/screenshot_service.py
computer_use_ootb_internal/computer_use_demo/gui_agent/llm_utils/llm_utils.py
computer_use_ootb_internal/computer_use_demo/gui_agent/llm_utils/oai.py
computer_use_ootb_internal/computer_use_demo/gui_agent/llm_utils/run_litellm.py
computer_use_ootb_internal/computer_use_demo/gui_agent/llm_utils/run_llm.py
computer_use_ootb_internal/computer_use_demo/tools/__init__.py
computer_use_ootb_internal/computer_use_demo/tools/aws_request.py
computer_use_ootb_internal/computer_use_demo/tools/base.py
computer_use_ootb_internal/computer_use_demo/tools/bash.py
computer_use_ootb_internal/computer_use_demo/tools/collection.py
computer_use_ootb_internal-0.0.196.dist-info/METADATA
computer_use_ootb_internal-0.0.196.dist-info/WHEEL
computer_use_ootb_internal-0.0.196.dist-info/entry_points.txt
computer_use_ootb_internal-0.0.196.dist-info/RECORD
