Metadata-Version: 2.4
Name: computer-use-ootb-internal
Version: 0.0.196
Summary: Computer Use OOTB
Author-email: Siyuan Hu <siyuan.hu.sg@gmail.com>
Requires-Python: >=3.11
Requires-Dist: anthropic[bedrock,vertex]>=0.37.1
Requires-Dist: boto3>=1.28.57
Requires-Dist: flask>=2.0
Requires-Dist: google-auth<3,>=2
Requires-Dist: gradio>=5.6.0
Requires-Dist: jsonschema==4.22.0
Requires-Dist: litellm
Requires-Dist: matplotlib
Requires-Dist: opencv-python
Requires-Dist: psutil>=5.0; sys_platform == 'win32'
Requires-Dist: pyautogui==0.9.54
Requires-Dist: pywin32>=306; sys_platform == 'win32'
Requires-Dist: pywinauto; sys_platform == 'win32'
Requires-Dist: requests>=2.0
Requires-Dist: screeninfo
Requires-Dist: streamlit>=1.38.0
Requires-Dist: textdistance
Requires-Dist: uiautomation; sys_platform == 'win32'
Requires-Dist: waitress>=2.0
Provides-Extra: dev
Requires-Dist: pre-commit>=3.8.0; extra == 'dev'
Requires-Dist: pytest-asyncio>=0.23.6; extra == 'dev'
Requires-Dist: pytest>=8.3.3; extra == 'dev'
Requires-Dist: ruff>=0.6.7; extra == 'dev'
